code/__init__.py
ehfuweufh-1.0.dist-info/METADATA
ehfuweufh-1.0.dist-info/WHEEL
ehfuweufh-1.0.dist-info/top_level.txt
ehfuweufh-1.0.dist-info/RECORD
