Metadata-Version: 2.1
Name: ehfuweufh
Version: 1.0
Summary: Description of your package
Home-page: https://github.com/XredaX/liteium
Author: El Bettioui Reda
Author-email: redaelbettioui@gmail.com
Classifier: Programming Language :: Python :: 3
Classifier: License :: OSI Approved :: MIT License
Classifier: Operating System :: OS Independent
Requires-Dist: selenium
